pymimic/__init__.py
pymimic/basis.py
pymimic/design.py
pymimic/emulator.py
pymimic/kernel.py
pymimic/plot.py
pymimic/testfunc.py
pymimic/design_data/lhs_design_10_100.dat
pymimic/design_data/lhs_design_10_11.dat
pymimic/design_data/lhs_design_10_12.dat
pymimic/design_data/lhs_design_10_13.dat
pymimic/design_data/lhs_design_10_14.dat
pymimic/design_data/lhs_design_10_15.dat
pymimic/design_data/lhs_design_10_16.dat
pymimic/design_data/lhs_design_10_17.dat
pymimic/design_data/lhs_design_10_18.dat
pymimic/design_data/lhs_design_10_19.dat
pymimic/design_data/lhs_design_10_20.dat
pymimic/design_data/lhs_design_10_21.dat
pymimic/design_data/lhs_design_10_22.dat
pymimic/design_data/lhs_design_10_23.dat
pymimic/design_data/lhs_design_10_24.dat
pymimic/design_data/lhs_design_10_25.dat
pymimic/design_data/lhs_design_10_26.dat
pymimic/design_data/lhs_design_10_27.dat
pymimic/design_data/lhs_design_10_28.dat
pymimic/design_data/lhs_design_10_29.dat
pymimic/design_data/lhs_design_10_30.dat
pymimic/design_data/lhs_design_10_31.dat
pymimic/design_data/lhs_design_10_32.dat
pymimic/design_data/lhs_design_10_33.dat
pymimic/design_data/lhs_design_10_34.dat
pymimic/design_data/lhs_design_10_35.dat
pymimic/design_data/lhs_design_10_36.dat
pymimic/design_data/lhs_design_10_37.dat
pymimic/design_data/lhs_design_10_38.dat
pymimic/design_data/lhs_design_10_39.dat
pymimic/design_data/lhs_design_10_40.dat
pymimic/design_data/lhs_design_10_41.dat
pymimic/design_data/lhs_design_10_42.dat
pymimic/design_data/lhs_design_10_43.dat
pymimic/design_data/lhs_design_10_44.dat
pymimic/design_data/lhs_design_10_45.dat
pymimic/design_data/lhs_design_10_46.dat
pymimic/design_data/lhs_design_10_47.dat
pymimic/design_data/lhs_design_10_48.dat
pymimic/design_data/lhs_design_10_49.dat
pymimic/design_data/lhs_design_10_50.dat
pymimic/design_data/lhs_design_10_51.dat
pymimic/design_data/lhs_design_10_52.dat
pymimic/design_data/lhs_design_10_53.dat
pymimic/design_data/lhs_design_10_54.dat
pymimic-1.0.1.dist-info/LICENSE
pymimic-1.0.1.dist-info/METADATA
pymimic-1.0.1.dist-info/WHEEL
pymimic-1.0.1.dist-info/top_level.txt
pymimic-1.0.1.dist-info/RECORD
