Metadata-Version: 2.1
Name: pymimic
Version: 1.0.1
Summary: A pure-Python implementation of linear prediction
Home-page: https://github.com/AmeryGration/pymimic
Author: Amery Gration
Author-email: amerygration@hotmail.com
Classifier: Programming Language :: Python :: 3
Classifier: License :: OSI Approved :: GNU General Public License (GPL)
Classifier: Operating System :: OS Independent
Requires-Python: >=3.6.9
License-File: LICENSE
Requires-Dist: numpy >=1.19.5
Requires-Dist: scipy >=1.5.4
Requires-Dist: matplotlib >=3.3.4
